{
    "composable": {
        "ps_video": {
            "si": {
                        "port": 0,
                        "Description": "PS Video input path"
                },
            "mi": {
                        "port": 0,
                        "Description": "PS Video output path"
            }
        },
        "mipi": {
            "si": {
                        "port": 1,
                        "Description": "MIPI frontend PL path"
                },
            "mi": {
                        "port": 1,
                        "Description": "MIPI frontend PS path"
            }
        }
    }
}